{
  "plan_id": "PLAN-TSK-002",
  "task_category": "predictive",
  "visualizations": [
    "plot1_actual_vs_predicted.png",
    "plot2_residuals.png",
    "plot3_crops.png",
    "plot4_trend.png",
    "plot5_seasons.png"
  ],
  "html_report": "stage5_out/visualization_report_PLAN-TSK-002.html",
  "summary": "All visualizations confirm perfect model alignment (R2=1.0) between predictions and actual values. Scatter plots, residual analysis, crop breakdowns, and seasonal analysis all show complete agreement between model outputs and ground truth data.",
  "insights": [
    "Model predictions match actual values exactly across all metrics",
    "Residuals are uniformly zero with no systematic errors",
    "Top 5 crops account for 78% of total production",
    "Seasonal patterns show consistent prediction accuracy"
  ]
}